h3daemon/__init__.py
h3daemon/cli.py
h3daemon/daemon.py
h3daemon/ensure_pressed.py
h3daemon/errors.py
h3daemon/fixstreams.py
h3daemon/master.py
h3daemon/pidfile.py
h3daemon/port.py
h3daemon/portfile.py
h3daemon/tcp.py
h3daemon/worker.py
h3daemon-2.0.5.dist-info/METADATA
h3daemon-2.0.5.dist-info/WHEEL
h3daemon-2.0.5.dist-info/entry_points.txt
h3daemon-2.0.5.dist-info/licenses/LICENSE
h3daemon-2.0.5.dist-info/RECORD
