Metadata-Version: 2.4
Name: h3daemon
Version: 2.0.5
Summary: HMMER server
Author-email: Danilo Horta <horta@ebi.ac.uk>
License-Expression: MIT
License-File: LICENSE
Requires-Python: ~=3.9
Requires-Dist: deciphon-schema>=0.2.0
Requires-Dist: hmmer<4,>=3.4.0.2
Requires-Dist: loguru>=0.7.3
Requires-Dist: pidlockfile<0.4,>=0.3
Requires-Dist: psutil<7,>=6.1.1
Requires-Dist: python-daemon<4,>=3.1.0
Requires-Dist: tenacity<10,>=9.0.0
Provides-Extra: cli
Requires-Dist: typer<0.16,>=0.15.0; extra == 'cli'
